snapatac2-2.8.0.dist-info/RECORD
snapatac2-2.8.0.dist-info/WHEEL
snapatac2-2.8.0.dist-info/METADATA
snapatac2-2.8.0.dist-info/licenses/LICENSE
snapatac2/_snapatac2.cpython-312-darwin.so
snapatac2/_io.py
snapatac2/datasets.py
snapatac2/__init__.py
snapatac2/genome.py
snapatac2/_utils.py
snapatac2/metrics/__init__.py
snapatac2/tools/_clustering.py
snapatac2/tools/_smooth.py
snapatac2/tools/_diff.py
snapatac2/tools/__init__.py
snapatac2/tools/_embedding.py
snapatac2/tools/_integration.py
snapatac2/tools/_network.py
snapatac2/tools/_call_peaks.py
snapatac2/tools/_motif.py
snapatac2/tools/_misc.py
snapatac2/plotting/_base.py
snapatac2/plotting/__init__.py
snapatac2/plotting/_network.py
snapatac2/preprocessing/_knn.py
snapatac2/preprocessing/_recipe.py
snapatac2/preprocessing/__init__.py
snapatac2/preprocessing/_scanorama.py
snapatac2/preprocessing/_scrublet.py
snapatac2/preprocessing/_cell_calling.py
snapatac2/preprocessing/_harmony.py
snapatac2/preprocessing/_mnn_correct.py
snapatac2/preprocessing/_basic.py
snapatac2/export/__init__.py
