Metadata-Version: 2.3
Name: snapatac2
Version: 2.8.0
Classifier: Programming Language :: Rust
Classifier: Programming Language :: Python :: Implementation :: CPython
Classifier: Programming Language :: Python :: Implementation :: PyPy
Classifier: License :: OSI Approved :: MIT License
Requires-Dist: anndata >=0.8.0, <0.11.0
Requires-Dist: kaleido
Requires-Dist: multiprocess
Requires-Dist: macs3 >= 3.0, < 3.1
Requires-Dist: natsort
Requires-Dist: numpy >=1.16.0, <2.0.0
Requires-Dist: pandas >=1.0, <2.1.2
Requires-Dist: plotly >=5.19.0, <6.0.0
Requires-Dist: polars >=1.0, <2.0
Requires-Dist: pooch >=1.6.0, <2.0.0
Requires-Dist: igraph >=0.10.3
Requires-Dist: pyarrow
Requires-Dist: pyfaidx >=0.7.0, <0.8.0
Requires-Dist: rustworkx
Requires-Dist: scipy >=1.4, <2.0.0
Requires-Dist: scikit-learn >=1.0, <2.0.0
Requires-Dist: tqdm >=4.62
Requires-Dist: typeguard >=4.0
Requires-Dist: scanorama >=1.7.3 ; extra == 'recommend'
Requires-Dist: harmonypy >=0.0.9 ; extra == 'recommend'
Requires-Dist: xgboost >=1.4 ; extra == 'recommend'
Requires-Dist: umap-learn >=0.5.0 ; extra == 'recommend'
Requires-Dist: scanpy >=1.9 ; extra == 'recommend'
Requires-Dist: scvi-tools >=1.0 ; extra == 'recommend'
Requires-Dist: scikit-misc >=0.1.3 ; extra == 'recommend'
Requires-Dist: magic-impute >=2.0 ; extra == 'recommend'
Requires-Dist: pytest ; extra == 'test'
Requires-Dist: hypothesis ==6.72.4 ; extra == 'test'
Provides-Extra: recommend
Provides-Extra: test
License-File: LICENSE
Summary: SnapATAC2: Single-cell epigenomics analysis pipeline
Keywords: single-cell,biology
Home-Page: https://github.com/
Author: Kai Zhang <kai@kzhang.org>
Author-email: Kai Zhang <zhangkai33@westlake.edu.cn>
Maintainer-email: Kai Zhang <zhangkai33@westlake.edu.cn>
License: MIT
Requires-Python: >=3.9, <3.13
Project-URL: Homepage, https://kzhang.org/SnapATAC2/index.html
Project-URL: Documentation, https://kzhang.org/SnapATAC2/index.html
Project-URL: Repository, https://kzhang.org/SnapATAC2/
Project-URL: Issues, https://github.com/kaizhang/SnapATAC2/issues
Project-URL: Changelog, https://kzhang.org/SnapATAC2/version/dev/changelog.html
